MANIFEST.in
README.rst
setup.py
django_javascript_settings.egg-info/PKG-INFO
django_javascript_settings.egg-info/SOURCES.txt
django_javascript_settings.egg-info/dependency_links.txt
django_javascript_settings.egg-info/requires.txt
django_javascript_settings.egg-info/top_level.txt
javascript_settings/__init__.py
javascript_settings/configuration_builder.py
javascript_settings/context_processors.py
javascript_settings/finders.py
javascript_settings/models.py
javascript_settings/settings.py
javascript_settings/tests.py
javascript_settings/views.py
javascript_settings/templatetags/__init__.py
javascript_settings/templatetags/javascript_settings_tags.py
javascript_settings/test_urls/__init__.py
javascript_settings/test_urls/test_empty/__init__.py
javascript_settings/test_urls/test_empty/urls.py
javascript_settings/test_urls/test_filled1/__init__.py
javascript_settings/test_urls/test_filled1/urls.py
javascript_settings/test_urls/test_filled2/__init__.py
javascript_settings/test_urls/test_filled2/urls.py