Metadata-Version: 1.0
Name: django-javascript-settings
Version: 1.1.1
Summary: django-javascript-settings is a Django application that provides a way of passing settings for Django applications to JavaScript.
Home-page: UNKNOWN
Author: Tomasz Wysocki
Author-email: tomasz@wysocki.info
License: UNKNOWN
Platform: UNKNOWN
